haki_crawler/__init__.py
haki_crawler/appfigures.py
haki_crawler/sensortower.py
haki_crawler-0.7.dist-info/METADATA
haki_crawler-0.7.dist-info/WHEEL
haki_crawler-0.7.dist-info/top_level.txt
haki_crawler-0.7.dist-info/RECORD
